Classfile /home/main_user/Documents/Boot2Root_CTF/Bird/bird_flipped.class
  Last modified Mar 30, 2019; size 566 bytes
  MD5 checksum 7f513597783b04bdc954fa995066254c
  Compiled from "MyClass.java"
public class MyClass
  minor version: 0
  major version: 52
  flags: ACC_PUBLIC, ACC_SUPER
Constant pool:
   #1 = Methodref          #10.#20        // java/lang/Object."<init>":()V
   #2 = Class              #21            // java/lang/StringBuilder
   #3 = Methodref          #2.#20         // java/lang/StringBuilder."<init>":()V
   #4 = String             #22            // b00t2root{
   #5 = Methodref          #2.#23         // java/lang/StringBuilder.append:(Ljava/lang/String;)Ljava/lang/StringBuilder;
   #6 = Methodref          #2.#24         // java/lang/StringBuilder.append:(I)Ljava/lang/StringBuilder;
   #7 = String             #25            // }
   #8 = Methodref          #2.#26         // java/lang/StringBuilder.toString:()Ljava/lang/String;
   #9 = Class              #27            // MyClass
  #10 = Class              #28            // java/lang/Object
  #11 = Utf8               <init>
  #12 = Utf8               ()V
  #13 = Utf8               Code
  #14 = Utf8               LineNumberTable
  #15 = Utf8               main
  #16 = Utf8               ([Ljava/lang/String;)V
  #17 = Utf8               StackMapTable
  #18 = Utf8               SourceFile
  #19 = Utf8               MyClass.java
  #20 = NameAndType        #11:#12        // "<init>":()V
  #21 = Utf8               java/lang/StringBuilder
  #22 = Utf8               b00t2root{
  #23 = NameAndType        #29:#30        // append:(Ljava/lang/String;)Ljava/lang/StringBuilder;
  #24 = NameAndType        #29:#31        // append:(I)Ljava/lang/StringBuilder;
  #25 = Utf8               }
  #26 = NameAndType        #32:#33        // toString:()Ljava/lang/String;
  #27 = Utf8               MyClass
  #28 = Utf8               java/lang/Object
  #29 = Utf8               append
  #30 = Utf8               (Ljava/lang/String;)Ljava/lang/StringBuilder;
  #31 = Utf8               (I)Ljava/lang/StringBuilder;
  #32 = Utf8               toString
  #33 = Utf8               ()Ljava/lang/String;
{
  public MyClass();
    descriptor: ()V
    flags: ACC_PUBLIC
    Code:
      stack=1, locals=1, args_size=1
         0: aload_0
         1: invokespecial #1                  // Method java/lang/Object."<init>":()V
         4: return
      LineNumberTable:
        line 1: 0

  public static void main(java.lang.String[]);
    descriptor: ([Ljava/lang/String;)V
    flags: ACC_PUBLIC, ACC_STATIC
    Code:
      stack=2, locals=3, args_size=1
         0: iconst_0
         1: istore_1
         2: iconst_0
         3: istore_2
         4: iload_2
         5: sipush        1337
         8: if_icmpge     21
        11: iload_1
        12: iload_2
        13: iadd
        14: istore_1
        15: iinc          2, 1
        18: goto          4
        21: new           #2                  // class java/lang/StringBuilder
        24: dup
        25: invokespecial #3                  // Method java/lang/StringBuilder."<init>":()V
        28: ldc           #4                  // String b00t2root{
        30: invokevirtual #5                  // Method java/lang/StringBuilder.append:(Ljava/lang/String;)Ljava/lang/StringBuilder;
        33: iload_1
        34: invokevirtual #6                  // Method java/lang/StringBuilder.append:(I)Ljava/lang/StringBuilder;
        37: ldc           #7                  // String }
        39: invokevirtual #5                  // Method java/lang/StringBuilder.append:(Ljava/lang/String;)Ljava/lang/StringBuilder;
        42: invokevirtual #8                  // Method java/lang/StringBuilder.toString:()Ljava/lang/String;
        45: astore_2
        46: return
      LineNumberTable:
        line 3: 0
        line 4: 2
        line 5: 11
        line 4: 15
        line 7: 21
        line 8: 46
      StackMapTable: number_of_entries = 2
        frame_type = 253 /* append */
          offset_delta = 4
          locals = [ int, int ]
        frame_type = 250 /* chop */
          offset_delta = 16
}
SourceFile: "MyClass.java"
